odoo9_addon_sale_crm_medical_prescription-9.0.1.0.0-py2.7-nspkg.pth
odoo_addons/sale_crm_medical_prescription/__openerp__.py
odoo_addons/sale_crm_medical_prescription/__init__.py
odoo_addons/sale_crm_medical_prescription/README.rst
odoo_addons/sale_crm_medical_prescription/models/__init__.py
odoo_addons/sale_crm_medical_prescription/models/crm_lead.py
odoo_addons/sale_crm_medical_prescription/views/crm_lead_view.xml
odoo_addons/sale_crm_medical_prescription/wizards/medical_lead_wizard.py
odoo_addons/sale_crm_medical_prescription/wizards/medical_lead_wizard_view.xml
odoo_addons/sale_crm_medical_prescription/wizards/__init__.py
odoo_addons/sale_crm_medical_prescription/tests/test_medical_lead_wizard.py
odoo_addons/sale_crm_medical_prescription/tests/test_crm_lead.py
odoo_addons/sale_crm_medical_prescription/tests/__init__.py
odoo_addons/sale_crm_medical_prescription/demo/medical_prescription_order_line_demo.xml
odoo_addons/sale_crm_medical_prescription/demo/medical_medicament_demo.xml
odoo_addons/sale_crm_medical_prescription/demo/medical_patient_demo.xml
odoo_addons/sale_crm_medical_prescription/demo/medical_pharmacy_demo.xml
odoo_addons/sale_crm_medical_prescription/demo/medical_prescription_order_demo.xml
odoo_addons/sale_crm_medical_prescription/demo/medical_patient_medication_demo.xml
odoo_addons/sale_crm_medical_prescription/demo/crm_lead_demo.xml
odoo_addons/sale_crm_medical_prescription/demo/medical_physician_demo.xml
odoo_addons/sale_crm_medical_prescription/static/description/icon.png
odoo9_addon_sale_crm_medical_prescription-9.0.1.0.0.dist-info/top_level.txt
odoo9_addon_sale_crm_medical_prescription-9.0.1.0.0.dist-info/WHEEL
odoo9_addon_sale_crm_medical_prescription-9.0.1.0.0.dist-info/RECORD
odoo9_addon_sale_crm_medical_prescription-9.0.1.0.0.dist-info/metadata.json
odoo9_addon_sale_crm_medical_prescription-9.0.1.0.0.dist-info/DESCRIPTION.rst
odoo9_addon_sale_crm_medical_prescription-9.0.1.0.0.dist-info/METADATA
odoo9_addon_sale_crm_medical_prescription-9.0.1.0.0.dist-info/namespace_packages.txt
